{
    "schemaVersion": 1,
    "title": "Server State",
    "author": {
        "github": "whitphx",
        "displayName": "whitphx"
    },
    "links": {
        "github": "https://github.com/whitphx/streamlit-server-state",
        "pypi": "streamlit-server-state",
        "demo": "https://share.streamlit.io/whitphx/streamlit-server-state/main/app_chat_rooms.py",
        "docs": null
    },
    "media": {
        "image": null
    },
    "install": {
        "pip": "pip install streamlit-server-state"
    },
    "governance": {
        "enabled": true,
        "notes": null
    },
    "categories": [
        "Developer tools"
    ]
}
